searchanonamuse
